{"is_source_file": false, "format": "", "description": "", "external_files": [], "external_methods": [], "published": [], "classes": [], "methods": [], "calls": [], "search-terms": [], "state": 2, "file_id": 1, "knowledge_revision": 20, "git_revision": "1fe669d5d7169d7630d291a82796f32f946865db", "hash": "9a6caa3425ea57e20c71930f13b0c83c", "format-version": 4, "code-base-name": "tic_tac_toe_frontend", "filename": "README.md", "revision_history": [{"20": "1fe669d5d7169d7630d291a82796f32f946865db"}]}